{"createdDate":"2025-08-31T22:15:14Z","activityEntities":["dataSourceMetrics",[{"title":"Data Summary","createdDate":"2025-08-31T22:26:49Z","event":"dataSourceMetrics","id":"BF1A22E0-696D-4F80-B69C-408C15B2C0E3","subtitle":"10 Classes, 126 Items"},{"event":"dataSourceMetrics","title":"Data Summary","createdDate":"2025-08-31T22:40:20Z","subtitle":"10 Classes, 241 Items","id":"52171E8D-36B5-47EA-B24A-B3E1ABE04A63"},{"title":"Data Summary","id":"886A2F44-98E2-4AEB-9F61-D8A5CC6BACAA","createdDate":"2025-08-31T22:49:09Z","event":"dataSourceMetrics","subtitle":"10 Classes, 241 Items"},{"id":"D73A3E56-93B8-4C43-BD96-2579F18C838B","title":"Data Summary","subtitle":"10 Classes, 516 Items","createdDate":"2025-08-31T22:58:58Z","event":"dataSourceMetrics"},{"title":"Data Summary","subtitle":"10 Classes, 367 Items","id":"CB952317-5B0C-43F0-B749-115D95522969","event":"dataSourceMetrics","createdDate":"2025-08-31T23:21:58Z"}],"dataSourceCreated",[{"id":"7B96A876-4A33-49F8-A0D1-ABA21A899DB3","event":"dataSourceCreated","subtitle":"zunlo_intents.csv","title":"Data Source Created","createdDate":"2025-08-31T22:15:14Z"}],"dataSourceTrainingStarted",[{"title":"Used By","id":"DE2E3943-8E45-4077-ADAC-B9C2D8DA786E","createdDate":"2025-08-31T22:26:49Z","event":"dataSourceTrainingStarted","subtitle":"ZunloTextClassifier 1"},{"subtitle":"ZunloTextClassifier 1","event":"dataSourceTrainingStarted","title":"Used By","createdDate":"2025-08-31T22:40:20Z","id":"57D198EB-2BC9-4048-9C6F-7CEDA1558535"},{"id":"AD1D1CB9-E988-4525-8943-00C74DB25C7B","createdDate":"2025-08-31T22:49:09Z","event":"dataSourceTrainingStarted","subtitle":"ZunloTextClassifier 1","title":"Used By"},{"id":"95A05AA8-7A36-438B-BCA9-6425F9103811","subtitle":"ZunloTextClassifier 1","title":"Used By","event":"dataSourceTrainingStarted","createdDate":"2025-08-31T22:58:58Z"},{"title":"Used By","subtitle":"ZunloTextClassifier 1","createdDate":"2025-08-31T23:21:58Z","id":"2616BF66-25BA-4BCC-844C-F1CE784624E0","event":"dataSourceTrainingStarted"}]],"version":"1.0","modifiedDate":"2025-09-01T15:32:46Z","pathType":0,"preferredFilename":"zunlo_intents","dataResult":{"classesCount":10,"dataSourceID":"DFC6FEA0-CCBF-4880-A967-8343C1E5DBAF","itemsCount":367,"dataAnalysis":{"issues":[{"description":"10 classes found, including reschedule_task, create_task, update_task","severity":"debug"},{"description":"367 texts found, automatically creating validation set","severity":"good"},{"severity":"debug","description":"Smallest class is \"plan_day\" with 14 texts"},{"severity":"debug","description":"Largest class is \"reschedule_task\" with 48 text"}],"summary":{"canUseValidation":1,"classCount":10,"sampleCount":367},"objectDetectorAnalysis":{"details":{}},"classifierAnalysis":{"labelStats":{"reschedule_event":48,"update_event":48,"plan_day":14,"create_event":48,"update_task":48,"reschedule_task":48,"plan_week":15,"show_agenda":18,"unknown":32,"create_task":48}}},"createdDate":"2025-08-31T22:15:14Z","dataURL":"file:\/\/\/Users\/marciogarcia\/dev\/loginode\/Zunlo\/ml\/zunlo_intents.csv"},"dataPathRelativeToProjectURL":"..\/zunlo_intents.csv\/","experimentIDs":["A616E8CC-2C6B-4411-990B-03E1DC9FB5E8"],"id":"DFC6FEA0-CCBF-4880-A967-8343C1E5DBAF","dataURL":"file:\/\/\/Users\/marciogarcia\/dev\/loginode\/Zunlo\/ml\/zunlo_intents.csv","title":"zunlo_intents.csv"}